hwave/__init__.py
hwave/dos.py
hwave/qlms.py
hwave/qlmsio/__init__.py
hwave/qlmsio/read_input.py
hwave/qlmsio/read_input_k.py
hwave/qlmsio/wan90.py
hwave/solver/__init__.py
hwave/solver/base.py
hwave/solver/perf.py
hwave/solver/rpa.py
hwave/solver/uhfk.py
hwave/solver/uhfr.py
hwave-1.0.1.dist-info/LICENSE
hwave-1.0.1.dist-info/METADATA
hwave-1.0.1.dist-info/WHEEL
hwave-1.0.1.dist-info/entry_points.txt
hwave-1.0.1.dist-info/RECORD
